bminf/__init__.py
bminf/version.py
bminf/wrapper.py
bminf/kernels/__init__.py
bminf/kernels/scale.fatbin
bminf/quantization/__init__.py
bminf/scheduler/__init__.py
bminf-2.0.1.dist-info/LICENSE
bminf-2.0.1.dist-info/METADATA
bminf-2.0.1.dist-info/WHEEL
bminf-2.0.1.dist-info/top_level.txt
bminf-2.0.1.dist-info/RECORD
