Metadata-Version: 2.1
Name: bminf
Version: 2.0.1
Summary: A toolkit for big model inference
Home-page: UNKNOWN
Author: a710128
Author-email: qbjooo@qq.com
License: UNKNOWN
Platform: UNKNOWN
Classifier: Programming Language :: Python :: 3
Classifier: License :: OSI Approved :: MIT License
Classifier: Programming Language :: C++
Requires-Python: >=3.6
Requires-Dist: torch
Requires-Dist: cpm-kernels (>=1.0.9)
Requires-Dist: typing-extensions
